general_ner/CRF.py
general_ner/NCRF.py
general_ner/__init__.py
general_ner/attention.py
general_ner/bert_crop.py
general_ner/clr_schedule.py
general_ner/config.py
general_ner/data_loader.py
general_ner/embedders.py
general_ner/lamb_optimizer.py
general_ner/metrics.py
general_ner/ner.py
general_ner/ner_models.py
general_ner/parse_sequence.py
general_ner/utils.py
general_ner-0.0.9.dist-info/LICENSE
general_ner-0.0.9.dist-info/METADATA
general_ner-0.0.9.dist-info/WHEEL
general_ner-0.0.9.dist-info/top_level.txt
general_ner-0.0.9.dist-info/RECORD
