Metadata-Version: 2.1
Name: general-ner
Version: 0.0.9
Summary: seq2seq_labeling
Home-page: https://github.com/kunpeng199494/general_ner
Author: feiyang
Author-email: duanqy1995@gmail.com
License: UNKNOWN
Project-URL: Source, https://github.com/kunpeng199494/general_ner
Keywords: seq2seq_labeling
Platform: UNKNOWN
Classifier: Development Status :: 3 - Alpha
Classifier: Intended Audience :: Developers
Classifier: Topic :: Software Development :: Build Tools
Classifier: License :: OSI Approved :: MIT License
Classifier: Programming Language :: Python :: 3.6
Classifier: Programming Language :: Python :: 3.7
Requires-Python: >=3.6, <4
Requires-Dist: hao
Requires-Dist: sklearn
Requires-Dist: torch (>=1.5.0)
Requires-Dist: numpy
Requires-Dist: transformers (==4.2.2)
Provides-Extra: dev
Provides-Extra: test
Requires-Dist: pytest ; extra == 'test'
